{
  "id": "webdev_web_development_implementation_steps_part_4b",
  "title": "Web Development Implementation Steps Part 4B",
  "technology": "Web Development",
  "module": "Web Development Iteration loops & State Traversal",
  "estimatedTime": 60,
  "difficultyLevels": [
    "beginner",
    "intermediate",
    "expert"
  ],
  "prerequisites": [],
  "nextLessons": [],
  "learningObjectives": [
    "Understand Web Development Implementation Steps Part 4B from zero to advanced level",
    "Write clean, production-grade Web Development code for Web Development Implementation Steps Part 4B",
    "Debug edge cases and answer interview questions about Web Development Implementation Steps Part 4B"
  ],
  "tags": [
    "web_development_implementation_steps_part_4b",
    "webdev",
    "web_development_iteration_loops_state_traversal"
  ]
}