{
  "id": "ml_machine_learning_implementation_steps_part_6b",
  "title": "Machine Learning Implementation Steps Part 6B",
  "technology": "Machine Learning",
  "module": "Machine Learning Data Collections & List Structures",
  "estimatedTime": 60,
  "difficultyLevels": [
    "beginner",
    "intermediate",
    "expert"
  ],
  "prerequisites": [],
  "nextLessons": [],
  "learningObjectives": [
    "Understand Machine Learning Implementation Steps Part 6B from zero to advanced level",
    "Write clean, production-grade Machine Learning code for Machine Learning Implementation Steps Part 6B",
    "Debug edge cases and answer interview questions about Machine Learning Implementation Steps Part 6B"
  ],
  "tags": [
    "machine_learning_implementation_steps_part_6b",
    "ml",
    "machine_learning_data_collections_list_structures"
  ]
}