{
  "id": "nextjs_next_js_developer_core_principles_part_7a",
  "title": "Next.js Developer Core Principles Part 7A",
  "technology": "Next.js Developer",
  "module": "Next.js Developer Advanced Abstractions & Type Blueprints",
  "estimatedTime": 60,
  "difficultyLevels": [
    "beginner",
    "intermediate",
    "expert"
  ],
  "prerequisites": [],
  "nextLessons": [],
  "learningObjectives": [
    "Understand Next.js Developer Core Principles Part 7A from zero to advanced level",
    "Write clean, production-grade Next.js Developer code for Next.js Developer Core Principles Part 7A",
    "Debug edge cases and answer interview questions about Next.js Developer Core Principles Part 7A"
  ],
  "tags": [
    "next_js_developer_core_principles_part_7a",
    "nextjs",
    "next_js_developer_advanced_abstractions_type_blueprints"
  ]
}