{
  "id": "css_css_core_principles_part_10a",
  "title": "CSS Core Principles Part 10A",
  "technology": "CSS",
  "module": "CSS Package Orchestration & System Modules",
  "estimatedTime": 60,
  "difficultyLevels": [
    "beginner",
    "intermediate",
    "expert"
  ],
  "prerequisites": [],
  "nextLessons": [],
  "learningObjectives": [
    "Understand CSS Core Principles Part 10A from zero to advanced level",
    "Write clean, production-grade CSS code for CSS Core Principles Part 10A",
    "Debug edge cases and answer interview questions about CSS Core Principles Part 10A"
  ],
  "tags": [
    "css_core_principles_part_10a",
    "css",
    "css_package_orchestration_system_modules"
  ]
}