{
  "id": "express_express_js_developer_troubleshooting_part_8c",
  "title": "Express.js Developer Troubleshooting Part 8C",
  "technology": "Express.js Developer",
  "module": "Express.js Developer Error Handling & Diagnostic Operations",
  "estimatedTime": 60,
  "difficultyLevels": [
    "beginner",
    "intermediate",
    "expert"
  ],
  "prerequisites": [],
  "nextLessons": [],
  "learningObjectives": [
    "Understand Express.js Developer Troubleshooting Part 8C from zero to advanced level",
    "Write clean, production-grade Express.js Developer code for Express.js Developer Troubleshooting Part 8C",
    "Debug edge cases and answer interview questions about Express.js Developer Troubleshooting Part 8C"
  ],
  "tags": [
    "express_js_developer_troubleshooting_part_8c",
    "express",
    "express_js_developer_error_handling_diagnostic_operations"
  ]
}