{
  "id": "azure_azure_cloud_engineer_implementation_steps_part_9b",
  "title": "Azure Cloud Engineer Implementation Steps Part 9B",
  "technology": "Azure Cloud Engineer",
  "module": "Azure Cloud Engineer File Integration & Stream Buffers",
  "estimatedTime": 60,
  "difficultyLevels": [
    "beginner",
    "intermediate",
    "expert"
  ],
  "prerequisites": [],
  "nextLessons": [],
  "learningObjectives": [
    "Understand Azure Cloud Engineer Implementation Steps Part 9B from zero to advanced level",
    "Write clean, production-grade Azure Cloud Engineer code for Azure Cloud Engineer Implementation Steps Part 9B",
    "Debug edge cases and answer interview questions about Azure Cloud Engineer Implementation Steps Part 9B"
  ],
  "tags": [
    "azure_cloud_engineer_implementation_steps_part_9b",
    "azure",
    "azure_cloud_engineer_file_integration_stream_buffers"
  ]
}