{
  "id": "c_goto_statement_alert",
  "title": "Goto Statement Alert",
  "technology": "C Programming",
  "module": "Control Flow Conditions",
  "estimatedTime": 60,
  "difficultyLevels": [
    "beginner",
    "intermediate",
    "expert"
  ],
  "prerequisites": [],
  "nextLessons": [],
  "learningObjectives": [
    "Understand Goto Statement Alert from zero to advanced level",
    "Write clean, production-grade C Programming code for Goto Statement Alert",
    "Debug edge cases and answer interview questions about Goto Statement Alert"
  ],
  "tags": [
    "goto_statement_alert",
    "c",
    "control_flow_conditions"
  ]
}