{
  "id": "sql_sql_databases_core_principles_part_2a",
  "title": "SQL & Databases Core Principles Part 2A",
  "technology": "SQL & Databases",
  "module": "SQL & Databases Variables & Core Data Layouts",
  "estimatedTime": 120,
  "difficultyLevels": [
    "beginner",
    "intermediate",
    "expert"
  ],
  "prerequisites": [
    "Mastery of previous module: SQL & Databases Setup & Architecture Foundations"
  ],
  "nextLessons": [],
  "learningObjectives": [
    "Explain the core operational logic of SQL & Databases Core Principles Part 2A.",
    "Write error-free implementations utilizing SQL & Databases Core Principles Part 2A.",
    "Debug and optimize performance characteristics of SQL & Databases Core Principles Part 2A."
  ],
  "tags": [
    "sql",
    "&",
    "databases",
    "core",
    "principles",
    "part",
    "2a"
  ]
}