{
  "id": "azure_azure_cloud_engineer_implementation_steps_part_11b",
  "title": "Azure Cloud Engineer Implementation Steps Part 11B",
  "technology": "Azure Cloud Engineer",
  "module": "Azure Cloud Engineer Performance Optimization & Complexity",
  "estimatedTime": 60,
  "difficultyLevels": [
    "beginner",
    "intermediate",
    "expert"
  ],
  "prerequisites": [],
  "nextLessons": [],
  "learningObjectives": [
    "Understand Azure Cloud Engineer Implementation Steps Part 11B from zero to advanced level",
    "Write clean, production-grade Azure Cloud Engineer code for Azure Cloud Engineer Implementation Steps Part 11B",
    "Debug edge cases and answer interview questions about Azure Cloud Engineer Implementation Steps Part 11B"
  ],
  "tags": [
    "azure_cloud_engineer_implementation_steps_part_11b",
    "azure",
    "azure_cloud_engineer_performance_optimization_complexity"
  ]
}