{
  "id": "placement_placement_preparation_implementation_steps_part_3b",
  "title": "Placement Preparation Implementation Steps Part 3B",
  "technology": "Placement Preparation",
  "module": "Placement Preparation Control Flow & Boolean Logic Branching",
  "estimatedTime": 60,
  "difficultyLevels": [
    "beginner",
    "intermediate",
    "expert"
  ],
  "prerequisites": [],
  "nextLessons": [],
  "learningObjectives": [
    "Understand Placement Preparation Implementation Steps Part 3B from zero to advanced level",
    "Write clean, production-grade Placement Preparation code for Placement Preparation Implementation Steps Part 3B",
    "Debug edge cases and answer interview questions about Placement Preparation Implementation Steps Part 3B"
  ],
  "tags": [
    "placement_preparation_implementation_steps_part_3b",
    "placement",
    "placement_preparation_control_flow_boolean_logic_branching"
  ]
}