{
  "id": "css_css_troubleshooting_part_10c",
  "title": "CSS Troubleshooting Part 10C",
  "technology": "CSS",
  "module": "CSS Package Orchestration & System Modules",
  "estimatedTime": 60,
  "difficultyLevels": [
    "beginner",
    "intermediate",
    "expert"
  ],
  "prerequisites": [],
  "nextLessons": [],
  "learningObjectives": [
    "Understand CSS Troubleshooting Part 10C from zero to advanced level",
    "Write clean, production-grade CSS code for CSS Troubleshooting Part 10C",
    "Debug edge cases and answer interview questions about CSS Troubleshooting Part 10C"
  ],
  "tags": [
    "css_troubleshooting_part_10c",
    "css",
    "css_package_orchestration_system_modules"
  ]
}