{
  "id": "data-engineering_data_engineering_implementation_steps_part_7b",
  "title": "Data Engineering Implementation Steps Part 7B",
  "technology": "Data Engineering",
  "module": "Data Engineering Advanced Abstractions & Type Blueprints",
  "estimatedTime": 60,
  "difficultyLevels": [
    "beginner",
    "intermediate",
    "expert"
  ],
  "prerequisites": [],
  "nextLessons": [],
  "learningObjectives": [
    "Understand Data Engineering Implementation Steps Part 7B from zero to advanced level",
    "Write clean, production-grade Data Engineering code for Data Engineering Implementation Steps Part 7B",
    "Debug edge cases and answer interview questions about Data Engineering Implementation Steps Part 7B"
  ],
  "tags": [
    "data_engineering_implementation_steps_part_7b",
    "data-engineering",
    "data_engineering_advanced_abstractions_type_blueprints"
  ]
}