{
  "id": "backend_backend_development_core_principles_part_5a",
  "title": "Backend Development Core Principles Part 5A",
  "technology": "Backend Development",
  "module": "Backend Development Modular Functions & Signature Scopes",
  "estimatedTime": 60,
  "difficultyLevels": [
    "beginner",
    "intermediate",
    "expert"
  ],
  "prerequisites": [],
  "nextLessons": [],
  "learningObjectives": [
    "Understand Backend Development Core Principles Part 5A from zero to advanced level",
    "Write clean, production-grade Backend Development code for Backend Development Core Principles Part 5A",
    "Debug edge cases and answer interview questions about Backend Development Core Principles Part 5A"
  ],
  "tags": [
    "backend_development_core_principles_part_5a",
    "backend",
    "backend_development_modular_functions_signature_scopes"
  ]
}