{
  "id": "c_while_sentinel_loop",
  "title": "While Sentinel Loop",
  "technology": "C Programming",
  "module": "Loops Iterations",
  "estimatedTime": 60,
  "difficultyLevels": [
    "beginner",
    "intermediate",
    "expert"
  ],
  "prerequisites": [],
  "nextLessons": [],
  "learningObjectives": [
    "Understand While Sentinel Loop from zero to advanced level",
    "Write clean, production-grade C Programming code for While Sentinel Loop",
    "Debug edge cases and answer interview questions about While Sentinel Loop"
  ],
  "tags": [
    "while_sentinel_loop",
    "c",
    "loops_iterations"
  ]
}