{
  "id": "data-engineering_data_engineering_troubleshooting_part_9c",
  "title": "Data Engineering Troubleshooting Part 9C",
  "technology": "Data Engineering",
  "module": "Data Engineering File Integration & Stream Buffers",
  "estimatedTime": 60,
  "difficultyLevels": [
    "beginner",
    "intermediate",
    "expert"
  ],
  "prerequisites": [],
  "nextLessons": [],
  "learningObjectives": [
    "Understand Data Engineering Troubleshooting Part 9C from zero to advanced level",
    "Write clean, production-grade Data Engineering code for Data Engineering Troubleshooting Part 9C",
    "Debug edge cases and answer interview questions about Data Engineering Troubleshooting Part 9C"
  ],
  "tags": [
    "data_engineering_troubleshooting_part_9c",
    "data-engineering",
    "data_engineering_file_integration_stream_buffers"
  ]
}