{
  "id": "aws_aws_cloud_architect_troubleshooting_part_1c",
  "title": "AWS Cloud Architect Troubleshooting Part 1C",
  "technology": "AWS Cloud Architect",
  "module": "AWS Cloud Architect Setup & Architecture Foundations",
  "estimatedTime": 120,
  "difficultyLevels": [
    "beginner",
    "intermediate",
    "expert"
  ],
  "prerequisites": [
    "Basic computer literacy"
  ],
  "nextLessons": [],
  "learningObjectives": [
    "Explain the core operational logic of AWS Cloud Architect Troubleshooting Part 1C.",
    "Write error-free implementations utilizing AWS Cloud Architect Troubleshooting Part 1C.",
    "Debug and optimize performance characteristics of AWS Cloud Architect Troubleshooting Part 1C."
  ],
  "tags": [
    "aws",
    "cloud",
    "architect",
    "troubleshooting",
    "part",
    "1c"
  ]
}